hello_robot_stretch_body_dev-0.3.0.dist-info/DESCRIPTION.rst
hello_robot_stretch_body_dev-0.3.0.dist-info/METADATA
hello_robot_stretch_body_dev-0.3.0.dist-info/RECORD
hello_robot_stretch_body_dev-0.3.0.dist-info/WHEEL
hello_robot_stretch_body_dev-0.3.0.dist-info/metadata.json
hello_robot_stretch_body_dev-0.3.0.dist-info/top_level.txt
stretch_body/__init__.py
stretch_body/arm.py
stretch_body/base.py
stretch_body/cobbs_framing.py
stretch_body/device.py
stretch_body/dynamixel_XL430.py
stretch_body/dynamixel_X_chain.py
stretch_body/dynamixel_hello_XL430.py
stretch_body/end_of_arm.py
stretch_body/end_of_arm_tools.py
stretch_body/head.py
stretch_body/hello_utils.py
stretch_body/lift.py
stretch_body/pimu.py
stretch_body/robot.py
stretch_body/robot_collision.py
stretch_body/robot_collision_models.py
stretch_body/robot_monitor.py
stretch_body/robot_params.py
stretch_body/robot_params_RE1.0.py
stretch_body/robot_params_RE1.5.py
stretch_body/scope.py
stretch_body/stepper.py
stretch_body/stretch_gripper.py
stretch_body/trajectories.py
stretch_body/transport.py
stretch_body/version.py
stretch_body/wacc.py
stretch_body/wrist_yaw.py
stretch_body/xbox_controller.py
test/__init__.py
test/test_arm.py
test/test_base.py
test/test_collisions.py
test/test_device.py
test/test_dxl_comms.py
test/test_dynamixel_XL430.py
test/test_dynamixel_hello_XL430.py
test/test_end_of_arm.py
test/test_end_of_arm_tools.py
test/test_head.py
test/test_hello_utils.py
test/test_lift.py
test/test_pimu.py
test/test_robot.py
test/test_robot_params.py
test/test_steppers.py
test/test_stretch_gripper.py
test/test_sync.py
test/test_timing_stats.py
test/test_trajectories.py
test/test_wrist_yaw.py
