Metadata-Version: 2.0
Name: hello-robot-stretch-body-dev
Version: 0.3.0
Summary: Stretch RE1 low level Python API
Home-page: https://github.com/hello-robot/stretch_body
Author: Hello Robot Inc.
Author-email: support@hello-robot.com
License: UNKNOWN
Platform: UNKNOWN
Classifier: Programming Language :: Python :: 3
Classifier: Operating System :: OS Independent
Classifier: License :: OSI Approved :: GNU Lesser General Public License v3 (LGPLv3)
Requires-Dist: numpy
Requires-Dist: scipy
Requires-Dist: matplotlib
Requires-Dist: ipython
Requires-Dist: pandas
Requires-Dist: sympy
Requires-Dist: nose
Requires-Dist: inputs
Requires-Dist: drawnow
Requires-Dist: rplidar-roboticia
Requires-Dist: snakeviz
Requires-Dist: pyusb
Requires-Dist: SpeechRecognition
Requires-Dist: pixel-ring
Requires-Dist: click
Requires-Dist: cma
Requires-Dist: opencv-contrib-python
Requires-Dist: colorama
Requires-Dist: scikit-image
Requires-Dist: open3d
Requires-Dist: pyrealsense2
Requires-Dist: pathlib
Requires-Dist: psutil
Requires-Dist: gitpython
Requires-Dist: urdfpy
Requires-Dist: jupyter
Requires-Dist: numba
Requires-Dist: pyyaml (>=5.1)
Requires-Dist: hello-robot-stretch-tool-share (>=0.2.0)
Requires-Dist: jsonschema (==2.6.0); python_version < "3.0"
Requires-Dist: qtconsole (==4.7.7); python_version < "3.0"
Requires-Dist: llvmlite (==0.31.0); python_version < "3.0"
Requires-Dist: terminado (==0.8.3); python_version < "3.0"
Requires-Dist: dynamixel-sdk (>=3.1); python_version >= "3.0.0"
